ultra_cache/__init__.py
ultra_cache/build_cache_key.py
ultra_cache/cache_control.py
ultra_cache/decorator.py
ultra_cache/main.py
ultra_cache/py.typed
ultra_cache/storage/__init__.py
ultra_cache/storage/base.py
ultra_cache/storage/inmemory.py
ultra_cache/storage/redis.py
ultra_cache/utils.py
ultra_cache-0.2.0.dist-info/LICENSE
ultra_cache-0.2.0.dist-info/METADATA
ultra_cache-0.2.0.dist-info/WHEEL
ultra_cache-0.2.0.dist-info/RECORD
